P/ALU.v
module ALU(
    input [3:0] sel,
    input [31:0] A,
    input [31:0] B,
    output reg [31:0] out,
    output reg zeroflag
);

always @(*) begin
     
    case(sel)
        4'b0000: out = A + B;
        4'b0001: out = A - B;
        4'b0010: out = A ^ B;
        4'b0011: out = A | B;
        4'b0100: out = A & B;
        4'b0101: out = A << B; //ShiftLeftLogical
        4'b0110: out = A >> B; //ShiftRightLogical
        4'b0111: out = A >> B; //ShiftRightArith*
        4'b1000: out = (A < B) ? 1 : 0;
        4'b1001: out = (A < B) ? 1 : 0;

        default: out = 32'b0;
    
    endcase 

    zeroflag = (out == 32'b0); 
end

endmodule

P/testbench/ALU_tb.v
module ALU_tb();

//input 
 reg [3:0] sel;
 reg [31:0] A,B;

 wire [31:0] out;
 wire zeroflag;

 ALU uut(.sel(sel),
        .A(A),
        .B(B),
        .out(out),
        .zeroflag(zeroflag));

initial begin
  $dumpfile("alu_test.vcd");
  $dumpvars();
end

initial begin
  $monitor("A = %h , B = %h , sel = %b , out = %h, zeroflag = %b", A,B,sel,out, zeroflag);
end

initial begin
  A = 32'h0FFF1256;
  B = 32'h0011FF23;
  sel = 4'b0000;
  #10 sel = 4'b0001;
  #10 sel = 4'b0010;
  #10 sel = 4'b0011;
  #10 sel = 4'b0100;

  #5 B = 32'h5;
  #10 sel = 4'b0101;
  #10 sel = 4'b0110;
  #10 sel = 4'b0111;
  #10 sel = 4'b1000;
  #10 sel = 4'b1001;

  #5 B = 32'b0;
  #10 sel = 4'b0100;
end

endmodule

P/testbench/alu_test.vcd
$date
	Sun Oct 12 23:40:07 2025
$end
$version
	Icarus Verilog
$end
$timescale
	1s
$end
$scope module ALU_tb $end
$var wire 1 ! zeroflag $end
$var wire 32 " out [31:0] $end
$var reg 32 # A [31:0] $end
$var reg 32 $ B [31:0] $end
$var reg 4 % sel [3:0] $end
$scope module uut $end
$var wire 32 & A [31:0] $end
$var wire 32 ' B [31:0] $end
$var wire 4 ( sel [3:0] $end
$var reg 32 ) out [31:0] $end
$var reg 1 ! zeroflag $end
$upscope $end
$upscope $end
$enddefinitions $end
#0
$dumpvars
b10000000100010001000101111001 )
b0 (
b100011111111100100011 '
b1111111111110001001001010110 &
b0 %
b100011111111100100011 $
b1111111111110001001001010110 #
b10000000100010001000101111001 "
0!
$end
#10
b1111111011010001001100110011 "
b1111111011010001001100110011 )
b1 %
b1 (
#20
b1111111011101110110101110101 "
b1111111011101110110101110101 )
b10 %
b10 (
#30
b1111111111111111111101110111 "
b1111111111111111111101110111 )
b11 %
b11 (
#40
b100010001001000000010 "
b100010001001000000010 )
b100 %
b100 (
#45
b100 "
b100 )
b101 $
b101 '
#55
b11111111111000100100101011000000 "
b11111111111000100100101011000000 )
b101 %
b101 (
#65
b11111111111100010010010 "
b11111111111100010010010 )
b110 %
b110 (
#75
b111 %
b111 (
#85
1!
b0 "
b0 )
b1000 %
b1000 (
#95
b1001 %
b1001 (
#100
b0 $
b0 '
#110
b100 %
b100 (
