P/ID_EX.v
module ID_EX(
    input clk,
    input reset,
    input [6:0]funct7,
    input [4:0] rs2,
    input [4:0] rs1,
    input [2:0] funct3,
    input [4:0] rd,
    input [6:0] opcode,
    input [31:0] PC_n,
    output reg[6:0]funct7_n,
    output reg[4:0] rs2_n,
    output reg[4:0] rs1_n,
    output reg[2:0] funct3_n,
    output reg[4:0] rd_n,
    output reg[6:0] opcode_n,
    output reg [31:0] PC_new
);


always @(posedge clk) begin
  if(reset)begin
    funct7_n <= 7'b0;
    rs2_n <= 5'b0;
    rs1_n <= 5'b0;
    rd_n <= 5'b0;
    opcode_n <= 7'b0;
    PC_new <= 32'b0;
  end
  else begin
    funct7_n <= funct7;
    rs2_n <= rs2;
    rs1_n <= rs1;
    rd_n <= rd;
    opcode_n <= opcode;
    PC_new <= PC_n;
  end
end

endmodule

P/decoder.v
module decoder(
    input [31:0] instruction,
    output [6:0]func7,
    output [4:0] rs2,
    output [4:0] rs1,
    output [2:0] func3,
    output [4:0] rd,
    output [6:0] opcode
);

assign func7 = instruction[31:25];
assign rs2 = instruction[24:20];
assign rs1 = instruction[19:15];
assign func3 = instruction[14:12];
assign rd = instruction[11:7];
assign opcode = instruction[6:0];

endmodule

P/ID_tb.v
module ID_tb();

reg clk;
reg reset;
reg [31:0] PC_n;
reg [31:0] instr;

wire [6:0] funct7, opcode;
wire [4:0] rs1,rs2,rd;
wire [2:0] funct3;

decoder uut(.instruction(instr),
                .func3(funct3),
                .func7(funct7),
                .rs1(rs1),
                .rs2(rs2),
                .rd(rd),
                .opcode(opcode));

wire [6:0] funct7_n, opcode_n;
wire [4:0] rs1_n,rs2_n,rd_n;
wire [2:0] funct3_n;
wire [31:0] PC_new;

ID_EX uut2(.clk(clk),
            .reset(reset),
            .funct3(funct3),
            .funct7(funct7),
            .rs2(rs2),
            .rs1(rs1),
            .opcode(opcode),
            .PC_n(PC_n),
            .funct7_n(funct7_n),
            .rs2_n(rs2_n),
            .rs1_n(rs1_n),
            .funct3_n(funct3_n),
            .rd_n(rd_n),
            .opcode_n(opcode_n),
            .PC_new(PC_new));


always #10 clk = ~clk;

initial begin
  $dumpfile("ID_test.vcd");
  $dumpvars(0,ID_tb);
  $monitor("instruction = %b rs1 = %b rs2 = %b rd = %b opcode = %b funct3 = %b funct7 = %b rs1_n = %b , rs2_n = %b , rd_n = %b , opcode_n = %b , funct3_n = %B, funct7_n = %b", instr,rs1,rs2,rd,opcode,funct3,funct7,rs1_n, rs2_n,rd_n,opcode_n,funct3_n,funct7_n);
end

initial begin
  clk = 0;
  reset = 1;
  instr = 32'h00500113;
  PC_n = 32'h12;
  #10 reset = 0;

  #20 instr = 32'h00A00193;
  #20 instr = 32'h00002223;
  #20 $finish;
end

endmodule

P/testbench/ID_test.vcd
$date
	Wed Oct 15 11:13:53 2025
$end
$version
	Icarus Verilog
$end
$timescale
	1s
$end
$scope module ID_tb $end
$var wire 5 ! rs2_n [4:0] $end
$var wire 5 " rs2 [4:0] $end
$var wire 5 # rs1_n [4:0] $end
$var wire 5 $ rs1 [4:0] $end
$var wire 5 % rd_n [4:0] $end
$var wire 5 & rd [4:0] $end
$var wire 7 ' opcode_n [6:0] $end
$var wire 7 ( opcode [6:0] $end
$var wire 7 ) funct7_n [6:0] $end
$var wire 7 * funct7 [6:0] $end
$var wire 3 + funct3_n [2:0] $end
$var wire 3 , funct3 [2:0] $end
$var wire 32 - PC_new [31:0] $end
$var reg 32 . PC_n [31:0] $end
$var reg 1 / clk $end
$var reg 32 0 instr [31:0] $end
$var reg 1 1 reset $end
$scope module uut $end
$var wire 32 2 instruction [31:0] $end
$var wire 5 3 rs2 [4:0] $end
$var wire 5 4 rs1 [4:0] $end
$var wire 5 5 rd [4:0] $end
$var wire 7 6 opcode [6:0] $end
$var wire 7 7 func7 [6:0] $end
$var wire 3 8 func3 [2:0] $end
$upscope $end
$scope module uut2 $end
$var wire 32 9 PC_n [31:0] $end
$var wire 1 / clk $end
$var wire 3 : funct3 [2:0] $end
$var wire 7 ; funct7 [6:0] $end
$var wire 7 < opcode [6:0] $end
$var wire 5 = rd [4:0] $end
$var wire 1 1 reset $end
$var wire 5 > rs1 [4:0] $end
$var wire 5 ? rs2 [4:0] $end
$var reg 32 @ PC_new [31:0] $end
$var reg 3 A funct3_n [2:0] $end
$var reg 7 B funct7_n [6:0] $end
$var reg 7 C opcode_n [6:0] $end
$var reg 5 D rd_n [4:0] $end
$var reg 5 E rs1_n [4:0] $end
$var reg 5 F rs2_n [4:0] $end
$upscope $end
$upscope $end
$enddefinitions $end
#0
$dumpvars
bx F
bx E
bx D
bx C
bx B
bx A
bx @
b101 ?
b0 >
b10 =
b10011 <
b0 ;
b0 :
b10010 9
b0 8
b0 7
b10011 6
b10 5
b0 4
b101 3
b10100000000000100010011 2
11
b10100000000000100010011 0
0/
b10010 .
bx -
b0 ,
bx +
b0 *
bx )
b10011 (
bx '
b10 &
bx %
b0 $
bx #
b101 "
bx !
$end
#10
b0 -
b0 @
b0 '
b0 C
b0 %
b0 D
b0 #
b0 E
b0 !
b0 F
b0 )
b0 B
1/
#20
0/
01
#30
b10010 -
b10010 @
b10011 '
b10011 C
b10 %
b10 D
b101 !
b101 F
b0 +
b0 A
1/
#40
b1010 "
b1010 3
b1010 ?
b11 &
b11 5
b11 =
0/
b101000000000000110010011 0
b101000000000000110010011 2
#50
b11 %
b11 D
b1010 !
b1010 F
1/
#60
b0 "
b0 3
b0 ?
b10 ,
b10 8
b10 :
b100 &
b100 5
b100 =
b100011 (
b100011 6
b100011 <
0/
b10001000100011 0
b10001000100011 2
#70
b100011 '
b100011 C
b100 %
b100 D
b0 !
b0 F
b10 +
b10 A
1/
