ALU.v
module ALU (
    input [31:0] A, B,       // 32-bit ALU inputs
    input [3:0] ALU_Sel,     // 4-bit ALU operation selector
    output reg [31:0] ALU_Out,  // 32-bit ALU result
    output ZeroFlag           // Flag if result is zero
);
    
    assign ZeroFlag = (ALU_Out == 32'b0); // Zero flag set if ALU result is zero

    always @(*) begin
        case (ALU_Sel)
            4'b0000: ALU_Out = A & B;  // AND
            4'b0001: ALU_Out = A | B;  // OR
            4'b0010: ALU_Out = A + B;  // ADD
            4'b0011: ALU_Out = A << B; // SLL (Shift Left Logical)
            4'b0100: ALU_Out = A - B;  // SUB
            4'b0101: ALU_Out = A >> B; // SRL (Shift Right Logical)
            4'b0110: ALU_Out = A * B;  // MUL
            4'b0111: ALU_Out = A ^ B;  // XOR
            4'b1000: ALU_Out = (A < B) ? 1 : 0; // SLT (Set Less Than)
            default: ALU_Out = 32'b0;  // Default case
        endcase
    end

endmodule

ALU/ALU_tb.v
`timescale 1ns / 1ps
module ALU_tb;
//Inputs
reg[31:0] A, B;
reg[3:0] ALU_Sel;

//Output
wire[31:0] ALU_Out;
wire ZeroFlag;

//Instantiate the ALU
ALU uut(
    .A(A),
    .B(B),
    .ALU_Sel(ALU_Sel),
    .ALU_Out(ALU_Out),
    .ZeroFlag(ZeroFlag)
);

//Testing
initial begin
    $dumpfile("waveform.vcd");  // Creates the waveform file
    $dumpvars(0, ALU_tb); 
    $monitor("Time=%t, A=%d, B=%d, ALU_Sel= %b, ALU_OUT = %d, ZeroFlag = %b",
    $time, A, B, ALU_Sel, ALU_Out, ZeroFlag);

    // Test ADD
        A = 32'h00000005; B = 32'h00000003; ALU_Sel = 4'b0010; #10; // Expected: 8
        
        // Test SUB
        A = 32'h00000009; B = 32'h00000004; ALU_Sel = 4'b0100; #10; // Expected: 5

        // Test AND
        A = 32'h0000000F; B = 32'h000000F0; ALU_Sel = 4'b0000; #10; // Expected: 0

        // Test OR
        A = 32'h0000000F; B = 32'h000000F0; ALU_Sel = 4'b0001; #10; // Expected: 0xFF
        
        // Test XOR
        A = 32'h0000000F; B = 32'h000000F0; ALU_Sel = 4'b0111; #10; // Expected: 0xFF

        // Test Shift Left Logical (SLL)
        A = 32'h00000001; B = 32'h00000004; ALU_Sel = 4'b0011; #10; // Expected: 16

        // Test Shift Right Logical (SRL)
        A = 32'h00000010; B = 32'h00000002; ALU_Sel = 4'b0101; #10; // Expected: 4

        // Test Multiply (MUL)
        A = 32'h00000003; B = 32'h00000002; ALU_Sel = 4'b0110; #10; // Expected: 6

        // Test Zero Flag
        A = 32'h00000005; B = 32'h00000005; ALU_Sel = 4'b0100; #10; // SUB result = 0, ZeroFlag should be 1
        #100
        //End Simulation
    $finish;
end
endmodule

ALU/waveform.vcd
$date
	Wed Mar 05 11:53:31 2025
$end
$version
	Icarus Verilog
$end
$timescale
	1ps
$end
$scope module ALU_tb $end
$var wire 1 ! ZeroFlag $end
$var wire 32 " ALU_Out [31:0] $end
$var reg 32 # A [31:0] $end
$var reg 4 $ ALU_Sel [3:0] $end
$var reg 32 % B [31:0] $end
$scope module uut $end
$var wire 32 & A [31:0] $end
$var wire 4 ' ALU_Sel [3:0] $end
$var wire 32 ( B [31:0] $end
$var wire 1 ! ZeroFlag $end
$var reg 32 ) ALU_Out [31:0] $end
$upscope $end
$upscope $end
$enddefinitions $end
#0
$dumpvars
b1000 )
b11 (
b10 '
b101 &
b11 %
b10 $
b101 #
b1000 "
0!
$end
#10000
b101 "
b101 )
b100 $
b100 '
b100 %
b100 (
b1001 #
b1001 &
#20000
1!
b0 "
b0 )
b0 $
b0 '
b11110000 %
b11110000 (
b1111 #
b1111 &
#30000
0!
b11111111 "
b11111111 )
b1 $
b1 '
#40000
b111 $
b111 '
#50000
b10000 "
b10000 )
b11 $
b11 '
b100 %
b100 (
b1 #
b1 &
#60000
b100 "
b100 )
b101 $
b101 '
b10 %
b10 (
b10000 #
b10000 &
#70000
b110 "
b110 )
b110 $
b110 '
b11 #
b11 &
#80000
1!
b0 "
b0 )
b100 $
b100 '
b101 %
b101 (
b101 #
b101 &
