ALU.v
//ALU IC 74181
`timescale 1ns / 1ps

module alu(
    input [31:0] A , B, //input
    input [3:0] S, //select
    output reg [31:0] F, //output
    output reg zeroflag
);


always @(*) begin
    case(S)
        4'b0000: F = A + B;  // ADD
        4'b0001: F = A - B;  // SUB
        4'b0010: F = A << B;  // SLL
        4'b0011: F = (A < B) ? 1 : 0; // Sel less than
        4'b0100: F = A ^ B;  // XOR
        4'b0101: F = A >> B; // SRL (Shift Right Logical)
        4'b0110: F = A | B;  // OR
        4'b0111: F = A & B;  // AND
        4'b1000: F = (A < B) ? 1 : 0; // SLT (Set Less Than) logial
        default: F = 32'b0;  // Default case
    endcase

    zeroflag = (F == 32'b0);
end

endmodule

ALU/ALU_tb.v
module ALU_tb();
//input
reg [31:0] A, B;
reg [3:0] S;
//output
wire[31:0] F;
wire zeroflag;

alu uut(.A(A), .B(B), .S(S), .F(F), .zeroflag(zeroflag));

initial begin
    $dumpfile("waveform.vcd");  // Creates the waveform file
    $dumpvars(0, ALU_tb); 
    $monitor("Time=%t, A=%d, B=%d, ALU_Sel= %b, ALU_OUT = %d, ZeroFlag = %b",
    $time, A, B, S, F, zeroflag);
  A = 32'b00010010001101000101011001111000;
  B = 32'b10011001101011011011111011110000;
  #10
  //ADD
  S = 4'b0000;
  #10
  //Sub
  S = 4'b0001;
  #10//XOR
  
  S = 4'b0010;
  #10//Sel less than
  S=4'b0011;
  
  #10//OR
  S = 4'b0110;

  #10//AND
  S = 4'b0111;
  #10
    B= 4'b0100;
  S =4'b0100;
  #10//SLL
  #10//SRL
  S = 4'b0101;
  #10
  //defalut
  S=4'b1010;

  #10;
$finish; 
end
endmodule

ALU/waveform.vcd
$date
	Wed Jun 04 21:28:45 2025
$end
$version
	Icarus Verilog
$end
$timescale
	1ps
$end
$scope module ALU_tb $end
$var wire 1 ! zeroflag $end
$var wire 32 " F [31:0] $end
$var reg 32 # A [31:0] $end
$var reg 32 $ B [31:0] $end
$var reg 4 % S [3:0] $end
$scope module uut $end
$var wire 32 & A [31:0] $end
$var wire 32 ' B [31:0] $end
$var wire 4 ( S [3:0] $end
$var reg 32 ) F [31:0] $end
$var reg 1 ! zeroflag $end
$upscope $end
$upscope $end
$enddefinitions $end
#0
$dumpvars
b0 )
bx (
b10011001101011011011111011110000 '
b10010001101000101011001111000 &
bx %
b10011001101011011011111011110000 $
b10010001101000101011001111000 #
b0 "
1!
$end
#10000
0!
b10101011111000100001010101101000 "
b10101011111000100001010101101000 )
b0 %
b0 (
#20000
b1111000100001101001011110001000 "
b1111000100001101001011110001000 )
b1 %
b1 (
#30000
1!
b0 "
b0 )
b10 %
b10 (
#40000
0!
b1 "
b1 )
b11 %
b11 (
#50000
b10011011101111011111111011111000 "
b10011011101111011111111011111000 )
b110 %
b110 (
#60000
b10000001001000001011001110000 "
b10000001001000001011001110000 )
b111 %
b111 (
#70000
b10010001101000101011001111100 "
b10010001101000101011001111100 )
b100 %
b100 (
b100 $
b100 '
#90000
b1001000110100010101100111 "
b1001000110100010101100111 )
b101 %
b101 (
#100000
1!
b0 "
b0 )
b1010 %
b1010 (
