IM.v
module IM(
    input [31:0] PC,
    output reg [31:0] Instr
);

reg [31:0] memory[0:11]; // 11 instructions

initial begin
  $readmemh("instruction.hex", memory); //Load instruction from File
end

always @(*) begin
  Instr = memory[PC>>2] ;// Fetch Instruction
end
endmodule

PC.v
module PC(
    input clk,
    input rst,
    input [31:0] PC_next,
    output reg [31:0] PC
);

always @(posedge clk or posedge rst)begin
  if (rst)
    PC <= 32'b0;
  else 
    PC <= PC_next;
    $display("PC Updated: PC=%h, PC_next=%h", PC, PC_next);
end

endmodule

InstructionFetch/PC_IM_tb.v
module PC_IM_tb;
    reg clk,rst;
    reg [31:0] PC_next;
    wire [31:0] PC;
    wire [31:0] Instr;

    PC pc_inst(
        .clk(clk),
        .rst(rst),
        .PC_next(PC_next),
        .PC(PC)
    );

    IM im_inst(
        .PC(PC),
        .Instr(Instr)
    );

    always #5 clk = ~clk;

    initial begin
      $dumpfile("waveform.vcd");
      $dumpvars(0,PC_IM_tb);

      clk=0;
      rst = 1; #10;
      rst = 0; #10;

      PC_next = 4; #10;
      PC_next = 8; #10;
      PC_next = 12; #10;
      PC_next = 16; #10;

      $finish;
    end
endmodule

InstructionFetch/waveform.vcd
$date
	Thu Mar 06 09:44:25 2025
$end
$version
	Icarus Verilog
$end
$timescale
	1s
$end
$scope module PC_IM_tb $end
$var wire 32 ! PC [31:0] $end
$var wire 32 " Instr [31:0] $end
$var reg 32 # PC_next [31:0] $end
$var reg 1 $ clk $end
$var reg 1 % rst $end
$scope module im_inst $end
$var wire 32 & PC [31:0] $end
$var reg 32 ' Instr [31:0] $end
$upscope $end
$scope module pc_inst $end
$var wire 32 ( PC_next [31:0] $end
$var wire 1 $ clk $end
$var wire 1 % rst $end
$var reg 32 ) PC [31:0] $end
$upscope $end
$upscope $end
$enddefinitions $end
#0
$dumpvars
b0 )
bx (
bx '
b0 &
1%
0$
bx #
bx "
b0 !
$end
#5
1$
#10
0$
0%
#15
bx !
bx &
bx )
1$
#20
0$
b100 #
b100 (
#25
b100 !
b100 &
b100 )
1$
#30
0$
b1000 #
b1000 (
#35
b1000 !
b1000 &
b1000 )
1$
#40
0$
b1100 #
b1100 (
#45
b1100 !
b1100 &
b1100 )
1$
#50
0$
b10000 #
b10000 (
#55
b10000 !
b10000 &
b10000 )
1$
